classo/__init__.py
classo/_version.py
classo/alo.py
classo/compact_func.py
classo/cross_validation.py
classo/misc_functions.py
classo/path_alg.py
classo/solve_R1.py
classo/solve_R2.py
classo/solve_R3.py
classo/solve_R4.py
classo/solver.py
classo/stability_selection.py
c_lasso-1.0.11.dist-info/LICENSE
c_lasso-1.0.11.dist-info/METADATA
c_lasso-1.0.11.dist-info/WHEEL
c_lasso-1.0.11.dist-info/top_level.txt
c_lasso-1.0.11.dist-info/RECORD
